{
    "patterns": {
        "Are you": "I'm",
        "Why": "That is because",
        "Can you": "I can",
        "Will you": "I will",
        "Do you": "I do",
        "Have you": "I have",
        "Is he": "He is",
        "Is she": "She is",
        "What is": "It is",
        "Where is": "It is at",
        "How is": "It is",
        "When is": "It is",
        "Could you": "I could",
        "Would you": "I would",
        "Should you": "I should",
        "Shall we": "We shall",
        "Did you": "I did",
        "Does he": "He does",
        "Does she": "She does",
        "Are they": "They are",
        "How do": "This is how",
        "What do": "This is what",
        "Which is": "It is",
        "Tell me": "Here is",
        "Explain": "Let me explain",
        "Give me": "Here is",
        "Show me": "Here is",
        "Help me": "Here is some help",
        "Do we": "We do",
        "Can we": "We can",
        "Shall I": "I shall",
        "You": "I"
    },
    "default_response": "Null."
}
